mock.py
auto_mock_server-1.0.9.dist-info/METADATA
auto_mock_server-1.0.9.dist-info/WHEEL
auto_mock_server-1.0.9.dist-info/top_level.txt
auto_mock_server-1.0.9.dist-info/RECORD
